autrainer/__init__.py
autrainer/augmentations/__init__.py
autrainer/augmentations/abstract_augmentation.py
autrainer/augmentations/augmentation_manager.py
autrainer/augmentations/augmentation_pipeline.py
autrainer/augmentations/augmentation_wrappers.py
autrainer/augmentations/choice_augmentation.py
autrainer/augmentations/image_augmentations.py
autrainer/augmentations/sequential_augmentation.py
autrainer/augmentations/spectrogram_augmentations.py
autrainer/augmentations/spectrogram_warp_utils.py
autrainer/augmentations/utils.py
autrainer/cli/__init__.py
autrainer/core/__init__.py
autrainer/core/constants/__init__.py
autrainer/core/constants/abstract_constants.py
autrainer/core/constants/export_constants.py
autrainer/core/constants/naming_constants.py
autrainer/core/constants/training_constants.py
autrainer/core/plotting/__init__.py
autrainer/core/plotting/plot_base.py
autrainer/core/plotting/plot_metrics.py
autrainer/core/scripts/__init__.py
autrainer/core/scripts/abstract_postprocess_script.py
autrainer/core/scripts/abstract_preprocess_script.py
autrainer/core/scripts/abstract_script.py
autrainer/core/scripts/cli.py
autrainer/core/scripts/command_line_error.py
autrainer/core/scripts/create_script.py
autrainer/core/scripts/delete_failed_script.py
autrainer/core/scripts/delete_states_script.py
autrainer/core/scripts/fetch_script.py
autrainer/core/scripts/group_script.py
autrainer/core/scripts/inference_script.py
autrainer/core/scripts/list_script.py
autrainer/core/scripts/postprocess_script.py
autrainer/core/scripts/preprocess_script.py
autrainer/core/scripts/show_script.py
autrainer/core/scripts/train_script.py
autrainer/core/scripts/utils.py
autrainer/core/structs/__init__.py
autrainer/core/structs/abstract_data_struct.py
autrainer/core/structs/data_struct.py
autrainer/core/utils/__init__.py
autrainer/core/utils/bookkeeping.py
autrainer/core/utils/hardware.py
autrainer/core/utils/requirements.py
autrainer/core/utils/set_seed.py
autrainer/core/utils/silence.py
autrainer-0.9.1.dist-info/METADATA
autrainer-0.9.1.dist-info/WHEEL
autrainer-0.9.1.dist-info/entry_points.txt
autrainer-0.9.1.dist-info/licenses/LICENSE
autrainer-0.9.1.dist-info/RECORD
