Metadata-Version: 2.4
Name: autrainer
Version: 0.9.1
Summary: A Modular and Extensible Deep Learning Toolkit for Computer Audition Tasks.
Project-URL: Repository, https://github.com/autrainer/autrainer
Project-URL: Documentation, https://autrainer.github.io/autrainer/
Author-email: Simon Rampp <simon.rampp@tum.de>, Andreas Triantafyllopoulos <andreas.triantafyllopoulos@tum.de>, Manuel Milling <manuel.milling@tum.de>, "Björn W. Schuller" <schuller@tum.de>
License-Expression: MIT
License-File: LICENSE
Keywords: artificial intelligence,command-line,computer audition,deep learning,hydra-core,pytorch,yaml
Classifier: Operating System :: OS Independent
Classifier: Programming Language :: Python :: 3
Classifier: Programming Language :: Python :: 3.10
Classifier: Programming Language :: Python :: 3.11
Classifier: Programming Language :: Python :: 3.12
Classifier: Programming Language :: Python :: 3.13
Requires-Python: <3.14,>=3.10
Requires-Dist: audeer<3,>=2.2.1
Requires-Dist: audiofile<2,>=1.3.0
Requires-Dist: audmetric<2,>=1.2.0
Requires-Dist: audobject<0.8,>=0.7.11
Requires-Dist: audtorch<0.7,>=0.6.4
Requires-Dist: checksumdir<2,>=1.2.0
Requires-Dist: hydra-core<2,>=1.3.2
Requires-Dist: hydra-filter-sweeper<3,>=2.1.0
Requires-Dist: matplotlib<4,>=3.7.1
Requires-Dist: numpy<3,>=2.1.0
Requires-Dist: omegaconf<3,>=2.3.0
Requires-Dist: pandas<3,>=2.2.3
Requires-Dist: pillow<12,>=11.0.0
Requires-Dist: psutil<6,>=5.0.0
Requires-Dist: pyyaml<7,>=6.0.1
Requires-Dist: requests<3,>=2.31.0
Requires-Dist: scikit-learn<2,>=1.6.0
Requires-Dist: seaborn<0.14,>=0.13.0
Requires-Dist: speechbrain<2,>=1.0.0
Requires-Dist: timm<2,>=1.0.3
Requires-Dist: torch<3,>=2.0.0
Requires-Dist: torchaudio>=2.0.0
Requires-Dist: torchinfo<2,>=1.8.0
Requires-Dist: torchlibrosa<0.2,>=0.1.0
Requires-Dist: torchvision>=0.15.0
Requires-Dist: tqdm<5,>=4.66.1
Requires-Dist: transformers<5,>=4.34.0
Provides-Extra: albumentations
Requires-Dist: albumentations<3,>=2.0.0; extra == 'albumentations'
Provides-Extra: all
Requires-Dist: albumentations<3,>=2.0.0; extra == 'all'
Requires-Dist: audiomentations<1,>=0.43.0; extra == 'all'
Requires-Dist: latex<0.8,>=0.7.0; extra == 'all'
Requires-Dist: mlflow<4,>=3.0.0; extra == 'all'
Requires-Dist: opensmile<3,>=2.5.0; extra == 'all'
Requires-Dist: tensorboard<3,>=2.16.2; extra == 'all'
Requires-Dist: torch-audiomentations<0.12,>=0.11.1; extra == 'all'
Provides-Extra: audiomentations
Requires-Dist: audiomentations<1,>=0.43.0; extra == 'audiomentations'
Provides-Extra: latex
Requires-Dist: latex<0.8,>=0.7.0; extra == 'latex'
Provides-Extra: mlflow
Requires-Dist: mlflow<4,>=3.0.0; extra == 'mlflow'
Provides-Extra: opensmile
Requires-Dist: opensmile<3,>=2.5.0; extra == 'opensmile'
Provides-Extra: tensorboard
Requires-Dist: tensorboard<3,>=2.16.2; extra == 'tensorboard'
Provides-Extra: torch-audiomentations
Requires-Dist: torch-audiomentations<0.12,>=0.11.1; extra == 'torch-audiomentations'
